[{"data":{"id":"InspectCode","source":null,"target":null}},{"data":{"id":"56884177-3d21-4d14-9192-57e8d10d5102","source":"InspectCode","target":"Build"}},{"data":{"id":"Build","source":null,"target":null}},{"data":{"id":"6a6b185c-6295-4784-9fa9-06e4602dd6ea","source":"Build","target":"Clean"}},{"data":{"id":"79de92ff-d3e0-407b-b32a-49704fb844d4","source":"Build","target":"Restore"}},{"data":{"id":"Restore","source":null,"target":null}},{"data":{"id":"Clean","source":null,"target":null}},{"data":{"id":"ff8dea7d-8fcc-4f78-b88d-d8b340af8524","source":"Clean","target":"Show-Info"}},{"data":{"id":"04e28953-31d5-4e43-99f1-36f4baec1bbc","source":"Clean","target":"Print-AppVeyor-Environment-Variables"}},{"data":{"id":"Print-AppVeyor-Environment-Variables","source":null,"target":null}},{"data":{"id":"Show-Info","source":null,"target":null}}]