[{"data":{"id":"Publish-GitHub-Release","source":null,"target":null}},{"data":{"id":"91e57814-488e-4fea-ac76-9147661a1f1f","source":"Publish-GitHub-Release","target":"Package"}},{"data":{"id":"Package","source":null,"target":null}},{"data":{"id":"ed6e09f8-51c6-47f5-8f71-46cbad052b6b","source":"Package","target":"Export-Release-Notes"}},{"data":{"id":"ed32996d-8e2b-4354-a316-fd328bc8fd15","source":"Package","target":"Analyze"}},{"data":{"id":"0354f998-e17a-4a73-bc14-e96b4994ec7a","source":"Package","target":"Test"}},{"data":{"id":"0588c49a-f34a-4585-8aa8-2f62d796c559","source":"Package","target":"Create-NuGet-Packages"}},{"data":{"id":"ecfe4f68-59d9-47ef-a93b-d890ad4870dc","source":"Package","target":"Create-Chocolatey-Packages"}},{"data":{"id":"Create-Chocolatey-Packages","source":null,"target":null}},{"data":{"id":"3929d0d3-b50a-4ffd-b8dd-abee77597a5e","source":"Create-Chocolatey-Packages","target":"Clean"}},{"data":{"id":"46ae0167-dde4-44e2-a290-68ffce149834","source":"Create-Chocolatey-Packages","target":"Build"}},{"data":{"id":"Build","source":null,"target":null}},{"data":{"id":"8123aa25-9f18-456a-99ba-8bf8929e756e","source":"Build","target":"Clean"}},{"data":{"id":"506bab29-932d-4985-a58c-f52e527f1763","source":"Build","target":"Restore"}},{"data":{"id":"Restore","source":null,"target":null}},{"data":{"id":"Clean","source":null,"target":null}},{"data":{"id":"2c7c72af-3cf4-41be-8989-67e5a0024232","source":"Clean","target":"Show-Info"}},{"data":{"id":"a9b46b0b-20a7-4656-b418-93a89258414b","source":"Clean","target":"Print-AppVeyor-Environment-Variables"}},{"data":{"id":"Print-AppVeyor-Environment-Variables","source":null,"target":null}},{"data":{"id":"Show-Info","source":null,"target":null}},{"data":{"id":"Clean","source":null,"target":null}},{"data":{"id":"57439d5d-6880-4d78-be33-3bafc835dab4","source":"Clean","target":"Show-Info"}},{"data":{"id":"4a41b013-d19b-4957-94c5-1497afb8bb54","source":"Clean","target":"Print-AppVeyor-Environment-Variables"}},{"data":{"id":"Print-AppVeyor-Environment-Variables","source":null,"target":null}},{"data":{"id":"Show-Info","source":null,"target":null}},{"data":{"id":"Create-NuGet-Packages","source":null,"target":null}},{"data":{"id":"93519832-b23e-496b-bf41-725aacd5aad6","source":"Create-NuGet-Packages","target":"Clean"}},{"data":{"id":"7e25fe03-7afa-449e-a963-cfec1456eca8","source":"Create-NuGet-Packages","target":"Build"}},{"data":{"id":"Build","source":null,"target":null}},{"data":{"id":"92d1808d-12c7-45b2-8b75-2abd0273e013","source":"Build","target":"Clean"}},{"data":{"id":"e35592f7-566a-4031-abcc-f330c6481bd1","source":"Build","target":"Restore"}},{"data":{"id":"Restore","source":null,"target":null}},{"data":{"id":"Clean","source":null,"target":null}},{"data":{"id":"06ec8496-3c5f-44e9-bcfa-11225f259b0d","source":"Clean","target":"Show-Info"}},{"data":{"id":"1f2b8889-8f47-4898-8a70-d793dfd175d3","source":"Clean","target":"Print-AppVeyor-Environment-Variables"}},{"data":{"id":"Print-AppVeyor-Environment-Variables","source":null,"target":null}},{"data":{"id":"Show-Info","source":null,"target":null}},{"data":{"id":"Clean","source":null,"target":null}},{"data":{"id":"e04f7fe1-9999-431b-8043-0d04580196a2","source":"Clean","target":"Show-Info"}},{"data":{"id":"f6ea6dac-a304-4a4d-ba4d-c2da194fc06b","source":"Clean","target":"Print-AppVeyor-Environment-Variables"}},{"data":{"id":"Print-AppVeyor-Environment-Variables","source":null,"target":null}},{"data":{"id":"Show-Info","source":null,"target":null}},{"data":{"id":"Test","source":null,"target":null}},{"data":{"id":"e5bd470c-8223-4b7d-af27-a798b2212510","source":"Test","target":"Build"}},{"data":{"id":"f5c23a48-49c2-4167-95bf-62a5c6035efa","source":"Test","target":"Test-NUnit"}},{"data":{"id":"983c3e7c-8861-4fa5-ba98-3cb14ce5a489","source":"Test","target":"Test-xUnit"}},{"data":{"id":"0e6b88c8-35e6-47b2-ae26-61db5b9662ba","source":"Test","target":"Test-MSTest"}},{"data":{"id":"e43e09db-0ec8-408a-acad-8c059a7c93c5","source":"Test","target":"Test-VSTest"}},{"data":{"id":"093c2160-4928-4f44-bf83-6edcb210611c","source":"Test","target":"Test-Fixie"}},{"data":{"id":"Test-Fixie","source":null,"target":null}},{"data":{"id":"1ad9e3a6-7b1f-47f6-ae6b-bf83da831054","source":"Test-Fixie","target":"Install-OpenCover"}},{"data":{"id":"Install-OpenCover","source":null,"target":null}},{"data":{"id":"e5ffa122-c440-4955-a36a-28996f7e0f85","source":"Install-OpenCover","target":"Install-ReportUnit"}},{"data":{"id":"Install-ReportUnit","source":null,"target":null}},{"data":{"id":"9b459ccb-81d5-4f1b-9a5c-6474ad264ec4","source":"Install-ReportUnit","target":"Install-ReportGenerator"}},{"data":{"id":"Install-ReportGenerator","source":null,"target":null}},{"data":{"id":"154afdac-ceba-462d-8097-61b6051a04dc","source":"Install-ReportGenerator","target":"Build"}},{"data":{"id":"Build","source":null,"target":null}},{"data":{"id":"256c8d97-fc74-4796-bd77-c17d828c0100","source":"Build","target":"Clean"}},{"data":{"id":"8bd49bbd-b35a-430d-a259-2eca29a0a047","source":"Build","target":"Restore"}},{"data":{"id":"Restore","source":null,"target":null}},{"data":{"id":"Clean","source":null,"target":null}},{"data":{"id":"9ec1709d-dd9c-4f12-96b2-d8dd3ff1c269","source":"Clean","target":"Show-Info"}},{"data":{"id":"c4e56b4d-f1f0-4dc2-9e76-8890900242e7","source":"Clean","target":"Print-AppVeyor-Environment-Variables"}},{"data":{"id":"Print-AppVeyor-Environment-Variables","source":null,"target":null}},{"data":{"id":"Show-Info","source":null,"target":null}},{"data":{"id":"Test-VSTest","source":null,"target":null}},{"data":{"id":"3d84077b-71a7-4689-b974-7d6445bef492","source":"Test-VSTest","target":"Install-OpenCover"}},{"data":{"id":"Install-OpenCover","source":null,"target":null}},{"data":{"id":"e3acc095-b418-4a08-9850-0429fc90b159","source":"Install-OpenCover","target":"Install-ReportUnit"}},{"data":{"id":"Install-ReportUnit","source":null,"target":null}},{"data":{"id":"7d1bb63a-4501-46e2-9dfc-3edf0d43f244","source":"Install-ReportUnit","target":"Install-ReportGenerator"}},{"data":{"id":"Install-ReportGenerator","source":null,"target":null}},{"data":{"id":"866e78c0-fe7c-409d-96bf-eb49773bc169","source":"Install-ReportGenerator","target":"Build"}},{"data":{"id":"Build","source":null,"target":null}},{"data":{"id":"2ebcc1ab-3ae1-43bf-b6ba-74e68af0eb79","source":"Build","target":"Clean"}},{"data":{"id":"bd71a0ff-efe0-4ae5-8dab-854bba8d220d","source":"Build","target":"Restore"}},{"data":{"id":"Restore","source":null,"target":null}},{"data":{"id":"Clean","source":null,"target":null}},{"data":{"id":"78156a8e-e452-46d9-83a0-cdace425cb9c","source":"Clean","target":"Show-Info"}},{"data":{"id":"f463d08d-9518-4a8c-ad9e-93f722056bb4","source":"Clean","target":"Print-AppVeyor-Environment-Variables"}},{"data":{"id":"Print-AppVeyor-Environment-Variables","source":null,"target":null}},{"data":{"id":"Show-Info","source":null,"target":null}},{"data":{"id":"Test-MSTest","source":null,"target":null}},{"data":{"id":"426f8fc5-7a10-4a32-a0fc-03d80d504695","source":"Test-MSTest","target":"Install-OpenCover"}},{"data":{"id":"Install-OpenCover","source":null,"target":null}},{"data":{"id":"665c4faf-15e6-4f5e-b4cc-c281a3aa808e","source":"Install-OpenCover","target":"Install-ReportUnit"}},{"data":{"id":"Install-ReportUnit","source":null,"target":null}},{"data":{"id":"4daa46af-c5bf-4473-ba0a-4ece78d10bad","source":"Install-ReportUnit","target":"Install-ReportGenerator"}},{"data":{"id":"Install-ReportGenerator","source":null,"target":null}},{"data":{"id":"0822ecea-9c9f-4a27-b945-55a41c87852e","source":"Install-ReportGenerator","target":"Build"}},{"data":{"id":"Build","source":null,"target":null}},{"data":{"id":"daf0161f-f481-4d17-bd70-5a997505e4f6","source":"Build","target":"Clean"}},{"data":{"id":"48c36165-52ab-4597-a99a-92db2a057808","source":"Build","target":"Restore"}},{"data":{"id":"Restore","source":null,"target":null}},{"data":{"id":"Clean","source":null,"target":null}},{"data":{"id":"09513f84-df05-4b75-bf63-cc9e463378b2","source":"Clean","target":"Show-Info"}},{"data":{"id":"aefaace7-4756-4414-a7b6-edefd940c1b7","source":"Clean","target":"Print-AppVeyor-Environment-Variables"}},{"data":{"id":"Print-AppVeyor-Environment-Variables","source":null,"target":null}},{"data":{"id":"Show-Info","source":null,"target":null}},{"data":{"id":"Test-xUnit","source":null,"target":null}},{"data":{"id":"1ac9bada-6b09-488f-b477-ebf5a955e40f","source":"Test-xUnit","target":"Install-OpenCover"}},{"data":{"id":"Install-OpenCover","source":null,"target":null}},{"data":{"id":"0a19bd65-cc50-4487-abee-17e7d650c526","source":"Install-OpenCover","target":"Install-ReportUnit"}},{"data":{"id":"Install-ReportUnit","source":null,"target":null}},{"data":{"id":"807166ac-bb06-4cd2-b354-538235dead14","source":"Install-ReportUnit","target":"Install-ReportGenerator"}},{"data":{"id":"Install-ReportGenerator","source":null,"target":null}},{"data":{"id":"3fe5ff38-6534-4392-bb93-34ebfb02db49","source":"Install-ReportGenerator","target":"Build"}},{"data":{"id":"Build","source":null,"target":null}},{"data":{"id":"f3616d04-58ab-4fa7-9c9c-4478fb99df89","source":"Build","target":"Clean"}},{"data":{"id":"a7076de8-fcc3-458c-83a4-aa6433fe8663","source":"Build","target":"Restore"}},{"data":{"id":"Restore","source":null,"target":null}},{"data":{"id":"Clean","source":null,"target":null}},{"data":{"id":"42bdb581-6c42-4186-94c6-87d271180c35","source":"Clean","target":"Show-Info"}},{"data":{"id":"2f778b01-5654-43be-a2e0-91d280d2fe7f","source":"Clean","target":"Print-AppVeyor-Environment-Variables"}},{"data":{"id":"Print-AppVeyor-Environment-Variables","source":null,"target":null}},{"data":{"id":"Show-Info","source":null,"target":null}},{"data":{"id":"Test-NUnit","source":null,"target":null}},{"data":{"id":"6a1f4024-805a-4d27-ac14-332aef2fa313","source":"Test-NUnit","target":"Install-OpenCover"}},{"data":{"id":"Install-OpenCover","source":null,"target":null}},{"data":{"id":"499b7470-3faf-49ea-9b12-b3b5e99d80a9","source":"Install-OpenCover","target":"Install-ReportUnit"}},{"data":{"id":"Install-ReportUnit","source":null,"target":null}},{"data":{"id":"eeb6c6ed-14f8-420e-90b6-810cff95e69c","source":"Install-ReportUnit","target":"Install-ReportGenerator"}},{"data":{"id":"Install-ReportGenerator","source":null,"target":null}},{"data":{"id":"74ed0461-6fb7-45d4-b1de-50796e8cd68f","source":"Install-ReportGenerator","target":"Build"}},{"data":{"id":"Build","source":null,"target":null}},{"data":{"id":"d4c3d7ad-804e-4427-a719-8594d86929e7","source":"Build","target":"Clean"}},{"data":{"id":"6fbc9fc0-cdb7-4d73-bc27-1333896cc25f","source":"Build","target":"Restore"}},{"data":{"id":"Restore","source":null,"target":null}},{"data":{"id":"Clean","source":null,"target":null}},{"data":{"id":"dbfde1e9-1b18-4ec8-b67e-6611ff363a46","source":"Clean","target":"Show-Info"}},{"data":{"id":"8118efcc-cc59-4dd1-8854-5d290fe81c26","source":"Clean","target":"Print-AppVeyor-Environment-Variables"}},{"data":{"id":"Print-AppVeyor-Environment-Variables","source":null,"target":null}},{"data":{"id":"Show-Info","source":null,"target":null}},{"data":{"id":"Build","source":null,"target":null}},{"data":{"id":"8a6dd2f9-fbce-4c10-ad45-4086eefc1bce","source":"Build","target":"Clean"}},{"data":{"id":"2df0505e-66b1-4990-9a6b-23ee4137104b","source":"Build","target":"Restore"}},{"data":{"id":"Restore","source":null,"target":null}},{"data":{"id":"Clean","source":null,"target":null}},{"data":{"id":"7c031880-95e4-4ad4-aaed-3333c6767c9c","source":"Clean","target":"Show-Info"}},{"data":{"id":"b5787ef0-1964-4661-8a27-64973c91e068","source":"Clean","target":"Print-AppVeyor-Environment-Variables"}},{"data":{"id":"Print-AppVeyor-Environment-Variables","source":null,"target":null}},{"data":{"id":"Show-Info","source":null,"target":null}},{"data":{"id":"Analyze","source":null,"target":null}},{"data":{"id":"1950179e-dff6-4596-8e72-dc5e055abcdf","source":"Analyze","target":"DupFinder"}},{"data":{"id":"f53363a7-19a7-4939-8a19-f139f24a992d","source":"Analyze","target":"InspectCode"}},{"data":{"id":"InspectCode","source":null,"target":null}},{"data":{"id":"512bb457-472e-45f9-8fe3-5793aaacae68","source":"InspectCode","target":"Build"}},{"data":{"id":"Build","source":null,"target":null}},{"data":{"id":"75017d11-5642-49d2-99d8-b26f686b213e","source":"Build","target":"Clean"}},{"data":{"id":"38638b49-8a4d-447a-96b9-f60dddda6d41","source":"Build","target":"Restore"}},{"data":{"id":"Restore","source":null,"target":null}},{"data":{"id":"Clean","source":null,"target":null}},{"data":{"id":"2fca3983-7bf3-4989-90b4-4f6810d92757","source":"Clean","target":"Show-Info"}},{"data":{"id":"8e5016b1-c324-4de2-95d2-d46f51e8558a","source":"Clean","target":"Print-AppVeyor-Environment-Variables"}},{"data":{"id":"Print-AppVeyor-Environment-Variables","source":null,"target":null}},{"data":{"id":"Show-Info","source":null,"target":null}},{"data":{"id":"DupFinder","source":null,"target":null}},{"data":{"id":"12fa6d9c-b644-4268-9423-76781d26bbf2","source":"DupFinder","target":"Build"}},{"data":{"id":"Build","source":null,"target":null}},{"data":{"id":"a0626a4f-4272-4259-a7ad-0046091b4fbd","source":"Build","target":"Clean"}},{"data":{"id":"8df30eba-6238-4b3a-afa0-61be85f0b20c","source":"Build","target":"Restore"}},{"data":{"id":"Restore","source":null,"target":null}},{"data":{"id":"Clean","source":null,"target":null}},{"data":{"id":"d5bc756b-b5ff-4175-9a00-c0661b697416","source":"Clean","target":"Show-Info"}},{"data":{"id":"aaa18826-ee38-49c8-bcc8-fc8cdffac0fe","source":"Clean","target":"Print-AppVeyor-Environment-Variables"}},{"data":{"id":"Print-AppVeyor-Environment-Variables","source":null,"target":null}},{"data":{"id":"Show-Info","source":null,"target":null}},{"data":{"id":"Export-Release-Notes","source":null,"target":null}}]